db_multitenant/__init__.py
db_multitenant/__version__.py
db_multitenant/mapper.py
db_multitenant/middleware.py
db_multitenant/threadlocal.py
db_multitenant/utils.py
db_multitenant/cache/__init__.py
db_multitenant/cache/helper.py
db_multitenant/db/__init__.py
db_multitenant/db/backends/__init__.py
db_multitenant/db/backends/mysql/__init__.py
db_multitenant/db/backends/mysql/base.py
db_multitenant/db/backends/postgresql/__init__.py
db_multitenant/db/backends/postgresql/base.py
django_db_multitenant-0.3.2.dist-info/DESCRIPTION.rst
django_db_multitenant-0.3.2.dist-info/METADATA
django_db_multitenant-0.3.2.dist-info/RECORD
django_db_multitenant-0.3.2.dist-info/WHEEL
django_db_multitenant-0.3.2.dist-info/metadata.json
django_db_multitenant-0.3.2.dist-info/top_level.txt
