Metadata-Version: 1.1
Name: django-db-multitenant
Version: 0.3.2
Summary: Multitenant support for Django, using one tenant per database.
Home-page: https://github.com/mik3y/django-db-multitenant
Author: Mike Wakerly
Author-email: opensource@hoho.com
License: Apache
Keywords: django multitenant
Platform: UNKNOWN
Classifier: License :: OSI Approved :: Apache Software License
Classifier: Programming Language :: Python
Classifier: Programming Language :: Python :: 2.7
Classifier: Programming Language :: Python :: 3
Classifier: Programming Language :: Python :: 3.3
Classifier: Programming Language :: Python :: 3.4
Classifier: Programming Language :: Python :: 3.5
Classifier: Programming Language :: Python :: 3.6
Classifier: Programming Language :: Python :: Implementation :: CPython
Classifier: Programming Language :: Python :: Implementation :: PyPy
